ZoneSender/CanParserNodeClient.py
ZoneSender/CanStackNodeClient.py
ZoneSender/CanUdsNodeClient.py
ZoneSender/ConfigNodeClient.py
ZoneSender/DoIPUdsNodeClient.py
ZoneSender/LinParseNodeClient.py
ZoneSender/LinStackNodeClient.py
ZoneSender/LogReplayNodeClient.py
ZoneSender/SomeipNodeClient.py
ZoneSender/TcpIpNodeClient.py
ZoneSender/ZoneSenderApp.py
ZoneSender/ZoneSenderFramework.py
ZoneSender/ZoneSenderStone.py
ZoneSender/__init__.py
ZoneSender/AutoSARData/AutoSARData.py
ZoneSender/AutoSARData/__init__.py
ZoneSender/BlfIo/BlfIo.py
ZoneSender/BlfIo/BlfIoObjs.py
ZoneSender/BlfIo/__init__.py
ZoneSender/MongoAPI/MongoAPI.py
ZoneSender/MongoAPI/__init__.py
ZoneSender/ObjIo/CanDiagMessage.py
ZoneSender/ObjIo/CanFrame.py
ZoneSender/ObjIo/CanISignalPdu.py
ZoneSender/ObjIo/CanMessage.py
ZoneSender/ObjIo/CanSignal.py
ZoneSender/ObjIo/CanStackConfig.py
ZoneSender/ObjIo/DiagnosticEcuInfo.py
ZoneSender/ObjIo/DiagnosticEcuInfo_DoIP.py
ZoneSender/ObjIo/DoIPDiagMessage.py
ZoneSender/ObjIo/HardwareConfig.py
ZoneSender/ObjIo/LinFrame.py
ZoneSender/ObjIo/LinMessage.py
ZoneSender/ObjIo/LinSignal.py
ZoneSender/ObjIo/SomeipPackage.py
ZoneSender/ObjIo/SomeipServiceState.py
ZoneSender/ObjIo/ZoneSenderObject.py
ZoneSender/ObjIo/__init__.py
ZoneSender/Protos/CanParserNode_pb2.py
ZoneSender/Protos/CanParserNode_pb2_grpc.py
ZoneSender/Protos/CanStackNode_pb2.py
ZoneSender/Protos/CanStackNode_pb2_grpc.py
ZoneSender/Protos/Common_pb2.py
ZoneSender/Protos/Common_pb2_grpc.py
ZoneSender/Protos/ConfigNode_pb2.py
ZoneSender/Protos/ConfigNode_pb2_grpc.py
ZoneSender/Protos/LinParserNode_pb2.py
ZoneSender/Protos/LinParserNode_pb2_grpc.py
ZoneSender/Protos/LinStackNode_pb2.py
ZoneSender/Protos/LinStackNode_pb2_grpc.py
ZoneSender/Protos/LogReplayNode_pb2.py
ZoneSender/Protos/LogReplayNode_pb2_grpc.py
ZoneSender/Protos/ProcessNode_pb2.py
ZoneSender/Protos/ProcessNode_pb2_grpc.py
ZoneSender/Protos/ShareMemNode_pb2.py
ZoneSender/Protos/ShareMemNode_pb2_grpc.py
ZoneSender/Protos/SomeIpNode_pb2.py
ZoneSender-4.3.13.dist-info/METADATA
ZoneSender-4.3.13.dist-info/WHEEL
ZoneSender-4.3.13.dist-info/top_level.txt
ZoneSender-4.3.13.dist-info/RECORD
