Metadata-Version: 2.1
Name: ZoneSender
Version: 4.3.13
Summary: A Python Lib For Vehicle Simulate And Test
Author: ZoneSender
Author-email: bmwshucheng@126.com
Classifier: Programming Language :: Python :: 3
Classifier: License :: OSI Approved :: MIT License
Classifier: Operating System :: OS Independent
Requires-Python: >=3.8
Requires-Dist: beautifulsoup4 (==4.10.0)
Requires-Dist: grpcio (==1.44.0)
Requires-Dist: grpcio-tools (==1.44.0)
Requires-Dist: paho-mqtt (==1.6.1)
Requires-Dist: protobuf (==3.19.4)
Requires-Dist: six (==1.16.0)
Requires-Dist: soupsieve (==2.3.1)
Requires-Dist: orjson (==3.8)
Requires-Dist: pymongo (==4.3.3)
